mwrap/__init__.py
mwrap/commands.py
mwrap/diff.py
mwrap/find.py
mwrap/main.py
mwrap/parse.py
mwrap-0.0.1.dist-info/LICENSE.txt
mwrap-0.0.1.dist-info/METADATA
mwrap-0.0.1.dist-info/RECORD
mwrap-0.0.1.dist-info/WHEEL
mwrap-0.0.1.dist-info/entry_points.txt
mwrap-0.0.1.dist-info/top_level.txt
